{"config":{
    "version":2,
    "device_info":{"vid":"0xFEED","pid":"0x3060",
        "name":"1bit","manufacture":"1bit","description":"1-bit keyboard"},
    "matrix":{"debounce":1,"is_left_hand":1,"diode_direction":2,
        "rows":2,"cols":1,"device_rows":1,"device_cols":1,
        "row_pins":[10, 15],
        "col_pins":[12, 13],
        "layout":[1, 2]},
    "mode":"SINGLE","startup":1,
    "peripheral":{"max_interval":60,"min_interval":30,"slave_latency":7},
    "central":{"max_interval":60,"min_interval":30,"slave_latency":0},
    "led":{"pin":1,"num":10},
    "keymap":{"locale":"US","use_ascii":0}
}}
